<?xml version="1.0"?>
<!-- 
	Datcom version number3.5.5                         
-->

<!--


  ****************** IMPORTANT NOTICES **********************

	This file was generated by Datcom+ Pro, a superset of 
	the USAF Digital DATCOM program.
	This file is considered an intermediary file in the 
	DATCOM/JSBSim process. This file may be overwritten
	without warning, so any changes that you make in here 
	may be lost.

	If you intend to use this file as it is and modify it, 
	make sure that you take the necessary precautions to 
	prevent it from being overwritten, like renaming it.


	***********************************************************
	DISCLAIMER REQUIRED BY HQ USAF FOR PUBLIC RELEASE APPROVAL

	THIS SOFTWARE AND ANY ACCOMPANYING DOCUMENTATION
	IS RELEASED "AS IS".  THE U.S. GOVERNMENT MAKES NO
	WARRANTY OF ANY KIND, EXPRESS OR IMPLIED, CONCERNING
	THIS SOFTWARE AND ANY ACCOMPANYING DOCUMENTATION,
	INCLUDING, WITHOUT LIMITATION, ANY WARRANTIES OF
	MERCHANTABILITY OR FITNESS FOR A PARTICULAR PURPOSE.
	IN NO EVENT WILL THE U.S. GOVERNMENT BE LIABLE FOR ANY
	DAMAGES, INCLUDING LOST PROFITS, LOST SAVINGS OR OTHER
	INCIDENTAL OR CONSEQUENTIAL DAMAGES ARISING OUT OF THE 
	USE, OR INABILITY TO USE, THIS SOFTWARE OR ANY
	ACCOMPANYING DOCUMENTATION, EVEN IF INFORMED IN ADVANCE
	OF THE POSSIBILITY OF SUCH DAMAGES.

	***********************************************************"-->


<!-- **********************************************************************
        AERODYNAMICS
     *******************************************************************-->
<aerodynamics>

	<!-- ************************* 
	          Sign Conventions    
	     ************************* 

			Control displacements
				Stick    FWD  + / Aft -
				Stick    Left + / Right -
				Wheel    CCW  + / CW -
				Pedal    Left + / Right -
				Elevator trim Nose Up + / Nose down -

        Surfaces
				Elevator  TED + / TEU -
				R Ail     TED + / TEU -
				L Ail     TED + / TEU -
				Rudder    TEL + / TER -

        F&M, Accel, Rates, Displacements
				Pitch     Up  + / Down -
				Roll      Rgt + / Left -
				Yaw       Rgt + / Left -

        Other
				Alpha     Up  + / Down -
				Beta Wind in right ear + / Wind in left ear -
				Slip Ball right of center + / left of center -
	-->


	<!-- ************************************** 
	          ASSUMPTIONS AND LIMITATIONS

			There is no interaction between deflected surfaces modeled
			so there is no change in elevator effects with the flaps
			deflected, for example.

			Terms known to be missing from DATCOM:
				Ground effects
				Cyr, dCY_Rud, dCY_Ail, dCl_Rud, dCN_Rud

	     **************************************
	-->

	<!-- The following functions provide properties in different units than are native to JSBSim -->

	<function name="attitude/pitch-deg">
		<description>Pitch angle in degrees</description>
		<product>
			<property> attitude/pitch-rad </property>
			<property> RADIANS-TO-DEGREES </property>
		</product>
	</function>

	<function name="attitude/roll-deg">
		<description>Roll angle in degrees</description>
		<product>
			<property> attitude/roll-rad </property>
			<property> RADIANS-TO-DEGREES </property>
		</product>
	</function>

	<function name="attitude/heading-true-deg">
		<description>Roll angle in degrees</description>
		<product>
			<property> attitude/heading-true-rad </property>
			<property> RADIANS-TO-DEGREES </property>
		</product>
	</function>

	<function name="velocities/q-deg_sec">
		<description>Pitch rate in degrees per sec</description>
		<product>
			<property> velocities/q-aero-rad_sec </property>
			<property> RADIANS-TO-DEGREES </property>
		</product>
	</function>

	<function name="velocities/p-deg_sec">
		<description>Pitch rate in degrees per sec</description>
		<product>
			<property> velocities/p-aero-rad_sec </property>
			<property> RADIANS-TO-DEGREES </property>
		</product>
	</function>

	<function name="velocities/r-deg_sec">
		<description>Pitch rate in degrees per sec</description>
		<product>
			<property> velocities/r-aero-rad_sec </property>
			<property> RADIANS-TO-DEGREES </property>
		</product>
	</function>

	<function name="velocities/h-dot-fpm">
		<description>Rate of climb, feet per minute</description>
		<product>
			<property> velocities/h-dot-fps </property>
			<property> FPS-TO-FPM </property>
		</product>
	</function>


	<!-- ********************************************************************** 
                LIFT FORCE
	     ********************************************************************** -->

	<function name="aero/coefficient/CL_wbh">
		<description>
			Lift coefficient due to wing, body, and horizontal tail
		</description>
		<table>
			<independentVar lookup="row"> aero/alpha-deg </independentVar>
			<tableData>
				     -2.0000        -.0003
				       .0000         .0000
				      2.0000         .0003
				      4.0000         .0008
				      8.0000         .0020
				     12.0000         .0035
				     16.0000         .0053
				     20.0000         .0072
				     24.0000         .0093
				     28.0000         .0114
				     32.0000         .0135
				     36.0000         .0154
				     40.0000         .0172
				     45.0000         .0191
				     50.0000         .0203
				     60.0000         .0202
				     70.0000         .0164
				     89.0000         .0009
				    120.0000        -.0179
				    175.0000        -.0004
			</tableData>
		</table>
	</function>

	<function name="aero/derivative/CLq-per_deg">
		<description>
			Lift coefficient derivative due to pitch rate, per deg
		</description>
		<table>
			<independentVar lookup="row"> aero/alpha-deg </independentVar>
			<tableData>
				 -2.0000     .0000
				175.0000     .0000
			</tableData>
		</table>
	</function>

	<function name="aero/derivative/CLadot-per_deg">
		<description>
			Lift coefficient derivative due to AOA rate, per deg
			Important contributor to short period damping
		</description>
		<table>
			<independentVar lookup="row"> aero/alpha-deg </independentVar>
			<tableData>
				     -2.0000         .0000
				       .0000         .0000
				      2.0000         .0000
				      4.0000         .0000
				      8.0000         .0000
				     12.0000         .0000
				     16.0000         .0000
				     20.0000         .0000
				     24.0000         .0000
				     28.0000         .0000
				     32.0000         .0000
				     36.0000         .0000
				     40.0000         .0000
				     45.0000         .0000
				     50.0000         .0000
				     60.0000         .0000
				     70.0000         .0000
				     89.0000         .0000
				    120.0000         .0000
				    175.0000         .0000
			</tableData>
		</table>
	</function>

	<function name="aero/coefficient/dCL_Elev">
		<description>
			Lift coefficient increment due to elevator deflection.
			Positive surface deflection is trailing edge down.
		</description>
		<table>
			<independentVar lookup="row"> fcs/elevator-pos-deg </independentVar>
			<tableData>

				<!-- **********************************************
				     No surface deflections specified in input file
				     ********************************************** -->
				     -10.0     0.0
				      10.0     0.0

			</tableData>
		</table>
	</function>

	<axis name="LIFT">

		<function name="aero/force/lift-lbs">
			<description>
				Lift force = ( CL_wbh + CLq*q*cbar/(2*V) + CLadot*adot*cbar/(2*V) + dCL_Elev )
				             * q_bar * wing area
			</description>
			<product>
				<sum>
					<property> aero/coefficient/CL_wbh </property>
					<product>
						<property> aero/derivative/CLq-per_deg </property>
						<property> velocities/q-deg_sec </property>
						<property> aero/ci2vel </property>
					</product>
					<product>
						<property> aero/derivative/CLadot-per_deg </property>
						<property> aero/alphadot-deg_sec </property>
						<property> aero/ci2vel </property>
					</product>
					<property> aero/coefficient/dCL_Elev </property>
				</sum>
				<property> aero/qbar-psf </property>
				<property> metrics/Sw-sqft </property>
			</product>
		</function>

	</axis>

	<!-- ********************************************************************** 
                DRAG FORCE
	     ********************************************************************** -->

	<function name="aero/coefficient/CD_wbh">
		<description>
			Drag coefficient due to wing, body, and horizontal tail
			Main contributor to Phugoid damping: greater Cd, better damping
		</description>
		<table>
			<independentVar lookup="row"> aero/alpha-deg </independentVar>
			<tableData>
				     -2.0000         .0011
				       .0000         .0011
				      2.0000         .0011
				      4.0000         .0011
				      8.0000         .0013
				     12.0000         .0018
				     16.0000         .0025
				     20.0000         .0036
				     24.0000         .0051
				     28.0000         .0070
				     32.0000         .0093
				     36.0000         .0120
				     40.0000         .0153
				     45.0000         .0199
				     50.0000         .0249
				     60.0000         .0355
				     70.0000         .0455
				     89.0000         .0539
				    120.0000         .0304
				    175.0000        -.0010
			</tableData>
		</table>
	</function>

	<function name="aero/coefficient/CD_Gear">
		<description>
			Drag due to gear. Coefficient is an approximation.
		</description>
		<product>
			<property>gear/gear-pos-norm</property>
			<value> 0.02 </value>
		</product>
	</function>


	<function name="aero/coefficient/dCD_Elev">
		<description>
			Drag coefficient increment due to elevator deflection.
			Positive surface deflection is trailing edge down.
		</description>
		<table>
			<independentVar lookup="row"> aero/alpha-deg </independentVar>
			<independentVar lookup="column"> fcs/elevator-pos-deg </independentVar>
			<tableData>
								

				<!-- **********************************************
				     No surface deflections specified in input file
				     ********************************************** -->
				     -10.0     0.0
				      10.0     0.0

			</tableData>
		</table>
	</function>

	<axis name="DRAG">

		<function name="aero/force/drag-lbs">
			<description>
				Drag force = ( CD_wbh + CD_Gear + dCD_Elev )
				             * q_bar * wing area
			</description>
			<product>
				<sum>
					<property> aero/coefficient/CD_wbh </property>
					<property> aero/coefficient/CD_Gear </property>
					<property> aero/coefficient/dCD_Elev </property>
				</sum>
				<property> aero/qbar-psf </property>
				<property> metrics/Sw-sqft </property>
			</product>
		</function>

	</axis>

	<!-- ********************************************************************** 
                SIDE FORCE
	     ********************************************************************** -->

	<function name="aero/derivative/CYbeta-per_deg">
		<description>
			Side force coefficient derivative due to sideslip, per deg
			Contributes to damping of dutch roll mode
		</description>
		<table>
			<independentVar lookup="row"> aero/alpha-deg </independentVar>
			<tableData>
				 -2.0000    -.0002
				175.0000    -.0002
			</tableData>
		</table>
	</function>

	<function name="aero/derivative/CYp-per_deg">
		<description>
			Side Force coefficient derivative due to roll rate, per deg
		</description>
		<table>
			<independentVar lookup="row"> aero/alpha-deg </independentVar>
			<tableData>
				     -2.0000         .0000
				       .0000         .0000
				      2.0000         .0000
				      4.0000         .0000
				      8.0000         .0000
				     12.0000         .0000
				     16.0000         .0000
				     20.0000         .0000
				     24.0000         .0000
				     28.0000         .0000
				     32.0000         .0000
				     36.0000         .0000
				     40.0000         .0000
				     45.0000         .0000
				     50.0000         .0000
				     60.0000         .0000
				     70.0000         .0000
				     89.0000         .0000
				    120.0000         .0000
				    175.0000         .0000
			</tableData>
		</table>
	</function>

	<function name="aero/derivative/CYr-per_deg">
		<description>
			Side Force coefficient derivative due to yaw rate
			DATCOM does not calculate this term
			Effect is small
		</description>
		<table>
			<independentVar lookup="row"> velocities/r-rad_sec </independentVar>
			<tableData>
				 -2.0000     .0000
				   .0000     .0000
				  2.0000     .0000
			</tableData>
		</table>
	</function>

	<function name="aero/coefficient/dCY_Rud">
		<description>
			Side Force coefficient increment due to rudder
			DATCOM does not calculate this term
		</description>
		<table>
			<independentVar lookup="row"> fcs/rudder-pos-deg </independentVar>
			<tableData>
				-30.0000     .0000
				   .0000     .0000
				 30.0000     .0000
			</tableData>
		</table>

	</function>

	<axis name="SIDE">

		<function name="aero/force/side-lbs">
			<description>
				Side force = ( CYbeta*beta + CYp*p*b/(2*V) + CYr*r*b/(2*V) + CYdRud )
				             * q_bar * wing area
			</description>
			<product>
				<sum>
					<product>
						<property> aero/derivative/CYbeta-per_deg </property>
						<property> aero/beta-deg </property>
					</product>
					<product>
						<property> aero/derivative/CYp-per_deg </property>
						<property> velocities/p-deg_sec </property>
						<property> aero/bi2vel </property>
					</product>
					<product>
						<property> aero/derivative/CYr-per_deg </property>
						<property> velocities/r-deg_sec </property>
						<property> aero/bi2vel </property>
					</product>
					<property> aero/coefficient/dCY_Rud </property>
				</sum>
				<property> aero/qbar-psf </property>
				<property> metrics/Sw-sqft </property>
			</product>
		</function>

	</axis>

	<!-- ********************************************************************** 
                ROLL MOMENT
	     ********************************************************************** -->

	<function name="aero/derivative/Clbeta-per_deg">
		<description>
			Roll moment coefficient derivative due to sideslip
			Decrease of Clb to small negative value improves dutch roll damping
			High Positive value leads to excessive spiral instability
		</description>
		<table>
			<independentVar lookup="row"> aero/alpha-deg </independentVar>
			<tableData>
				     -2.0000         .0000
				       .0000         .0000
				      2.0000         .0000
				      4.0000         .0000
				      8.0000         .0000
				     12.0000         .0000
				     16.0000         .0000
				     20.0000         .0000
				     24.0000         .0000
				     28.0000         .0000
				     32.0000         .0000
				     36.0000         .0000
				     40.0000         .0000
				     45.0000         .0000
				     50.0000         .0000
				     60.0000         .0000
				     70.0000         .0000
				     89.0000         .0000
				    120.0000         .0000
				    175.0000         .0000
			</tableData>
		</table>
	</function>

	<function name="aero/derivative/Clp-per_deg">
		<description>
			Roll moment coefficient derivative due to roll rate
			Clp alone determines damping-in-roll characteristics
		</description>
		<table>
			<independentVar lookup="row"> aero/alpha-deg </independentVar>
			<tableData>
				     -2.0000         .0000
				       .0000         .0000
				      2.0000         .0000
				      4.0000         .0000
				      8.0000         .0000
				     12.0000         .0000
				     16.0000         .0000
				     20.0000         .0000
				     24.0000         .0000
				     28.0000         .0000
				     32.0000         .0000
				     36.0000         .0000
				     40.0000         .0000
				     45.0000         .0000
				     50.0000         .0000
				     60.0000         .0000
				     70.0000         .0000
				     89.0000         .0000
				    120.0000         .0000
				    175.0000         .0000
			</tableData>
		</table>
	</function>

	<function name="aero/derivative/Clr-per_deg">
		<description>
			Roll moment coefficient derivative due to yaw rate, per deg
			Considerable effect on spiral mode. 
			Large positive values leads to strong sprial instability
		</description>
		<table>
			<independentVar lookup="row"> aero/alpha-deg </independentVar>
			<tableData>
				     -2.0000         .0000
				       .0000         .0000
				      2.0000         .0000
				      4.0000         .0000
				      8.0000         .0000
				     12.0000         .0000
				     16.0000         .0000
				     20.0000         .0000
				     24.0000         .0000
				     28.0000         .0000
				     32.0000         .0000
				     36.0000         .0000
				     40.0000         .0000
				     45.0000         .0000
				     50.0000         .0000
				     60.0000         .0000
				     70.0000         .0000
				     89.0000         .0000
				    120.0000         .0000
				    175.0000         .0000
			</tableData>
		</table>
	</function>

	<function name="aero/coefficient/dCl_Rud">
		<description>
			Roll moment coefficient increment due to rudder
			DATCOM does not calculate this term
		</description>
		<table>
			<independentVar lookup="row"> fcs/rudder-pos-deg </independentVar>
			<tableData>
				-30.0000     .0000
				   .0000     .0000
				 30.0000     .0000
			</tableData>
		</table>
	</function>

	<axis name="ROLL">

		<function name="aero/moment/roll-lbsft">
			<description>
				Roll Moment = ( Clbeta*beta + Clp*p*b/(2*V) + Clr*r*b/(2*V) + dCl_Rud )
				             * q_bar * wing area * wing span
			</description>
			<product>
				<sum>
					<product>
						<property> aero/derivative/Clbeta-per_deg </property>
						<property> aero/beta-deg </property>
					</product>
					<product>
						<property> aero/derivative/Clp-per_deg </property>
						<property> velocities/p-deg_sec </property>
						<property> aero/bi2vel </property>
					</product>
					<product>
						<property> aero/derivative/Clr-per_deg </property>
						<property> velocities/r-deg_sec </property>
						<property> aero/bi2vel </property>
					</product>
					<property> aero/coefficient/dCl_Rud </property>
				</sum>
				<property> aero/qbar-psf </property>
				<property> metrics/Sw-sqft </property>
				<property> metrics/bw-ft </property>
			</product>
		</function>

	</axis>

	<!-- ********************************************************************** 
                PITCH MOMENT
	     ********************************************************************** -->

	<function name="aero/coefficient/CM_wbh">
		<description>
			Pitch moment coefficient as a function of alpha
			CM0 is included in this term
		</description>
		<table>
			<independentVar lookup="row"> aero/alpha-deg </independentVar>
			<tableData>
				     -2.0000        -.0001
				       .0000         .0000
				      2.0000         .0001
				      4.0000         .0001
				      8.0000         .0002
				     12.0000         .0001
				     16.0000         .0000
				     20.0000        -.0001
				     24.0000        -.0004
				     28.0000        -.0007
				     32.0000        -.0011
				     36.0000        -.0016
				     40.0000        -.0021
				     45.0000        -.0029
				     50.0000        -.0037
				     60.0000        -.0055
				     70.0000        -.0072
				     89.0000        -.0091
				    120.0000        -.0068
				    175.0000        -.0001
			</tableData>
		</table>
	</function>

	<function name="aero/derivative/CMq-per_deg">
		<description>
			Pitch moment coefficient derivative due to pitch rate, per deg
			Pitch damping derivative - Very important to short period damping of oscillations
		</description>
		<table>
			<independentVar lookup="row"> aero/alpha-deg </independentVar>
			<tableData>
				 -2.0000     .0000
				175.0000     .0000
			</tableData>
		</table>
	</function>

	<function name="aero/derivative/CMadot-per_deg">
		<description>
			Pitch moment coefficient derivative due to AOA rate, per deg
			Negative CMadot increase short period damping
		</description>
		<table>
			<independentVar lookup="row"> aero/alpha-deg </independentVar>
			<tableData>
				     -2.0000         .0000
				       .0000         .0000
				      2.0000         .0000
				      4.0000         .0000
				      8.0000         .0000
				     12.0000         .0000
				     16.0000         .0000
				     20.0000         .0000
				     24.0000         .0000
				     28.0000         .0000
				     32.0000         .0000
				     36.0000         .0000
				     40.0000         .0000
				     45.0000         .0000
				     50.0000         .0000
				     60.0000         .0000
				     70.0000         .0000
				     89.0000         .0000
				    120.0000         .0000
				    175.0000         .0000
			</tableData>
		</table>
	</function>

	<axis name="PITCH">

		<function name="aero/moment/pitch-lbsft">
			<description>
				Pitch Moment = ( CM_wbh + CMq*q*MAC/(2*V) + CMadot*adot*MAC/(2*V) )
				               * q_bar * wing area * wing MAC
			</description>
			<product>
				<sum>
					<property> aero/coefficient/CM_wbh </property>
					<product>
						<property> aero/derivative/CMq-per_deg </property>
						<property> velocities/q-deg_sec </property>
						<property> aero/ci2vel </property>
					</product>
					<product>
						<property> aero/derivative/CMadot-per_deg </property>
						<property> aero/alphadot-deg_sec </property>
						<property> aero/ci2vel </property>
					</product>
					<property> aero/coefficient/dCM_Elev </property>
				</sum>
				<property> aero/qbar-psf </property>
				<property> metrics/Sw-sqft </property>
				<property> metrics/cbarw-ft </property>
			</product>
		</function>

	</axis>

	<!-- ********************************************************************** 
                YAW MOMENT
	     ********************************************************************** -->

	<function name="aero/derivative/CNbeta-per_deg">
		<description>
			Yaw moment coefficient derivative due to sideslip, per deg
			Determines dutch roll and spiral characteristics
			Prevents side-slip and counters yawing moments
		</description>
		<table>
			<independentVar lookup="row"> aero/alpha-deg </independentVar>
			<tableData>
				 -2.0000     .0000
				175.0000     .0000
			</tableData>
		</table>
	</function>

	<function name="aero/derivative/CNp-per_deg">
		<description>
			Yaw moment coefficient derivative due to roll rate, per deg
			Reduces Dutch Roll damping. Positive value desireable
		</description>
		<table>
			<independentVar lookup="row"> aero/alpha-deg </independentVar>
			<tableData>
				     -2.0000         .0000
				       .0000         .0000
				      2.0000         .0000
				      4.0000         .0000
				      8.0000         .0000
				     12.0000         .0000
				     16.0000         .0000
				     20.0000         .0000
				     24.0000         .0000
				     28.0000         .0000
				     32.0000         .0000
				     36.0000         .0000
				     40.0000         .0000
				     45.0000         .0000
				     50.0000         .0000
				     60.0000         .0000
				     70.0000         .0000
				     89.0000         .0000
				    120.0000         .0000
				    175.0000         .0000
			</tableData>
		</table>
	</function>

	<function name="aero/derivative/CNr-per_deg">
		<description>
			Yaw moment coefficient derivative due to yaw rate, per deg
			Main contributor to damping of Dutch Roll
		</description>
		<table>
			<independentVar lookup="row"> aero/alpha-deg </independentVar>
			<tableData>
				     -2.0000         .0000
				       .0000         .0000
				      2.0000         .0000
				      4.0000         .0000
				      8.0000         .0000
				     12.0000         .0000
				     16.0000         .0000
				     20.0000         .0000
				     24.0000         .0000
				     28.0000         .0000
				     32.0000         .0000
				     36.0000         .0000
				     40.0000         .0000
				     45.0000         .0000
				     50.0000         .0000
				     60.0000         .0000
				     70.0000         .0000
				     89.0000         .0000
				    120.0000         .0000
				    175.0000         .0000
			</tableData>
		</table>
	</function>

	<function name="aero/coefficient/dCN_Rud">
		<description>
			Yaw coefficient increment due to rudder
			DATCOM does not calculate this, but a default value is supplied
		</description>
		<table>
			<independentVar lookup="row"> fcs/rudder-pos-deg </independentVar>
			<tableData>
				-10.0000    -.0100
				   .0000     .0000
				 10.0000     .0100
			</tableData>
		</table>
	</function>

	<axis name="YAW">

		<function name="aero/moment/yaw-lbsft">
			<description>
				Yaw Moment = ( CNbeta*beta + CNp*p*b/(2*V) + CNr*r*b/(2*V) + dCN_Rud )
				             * q_bar * wing area * wing span
			</description>
			<product>
				<sum>
					<product>
						<property> aero/derivative/CNbeta-per_deg </property>
						<property> aero/beta-deg </property>
					</product>
					<product>
						<property> aero/derivative/CNp-per_deg </property>
						<property> velocities/p-deg_sec </property>
						<property> aero/bi2vel </property>
					</product>
					<product>
						<property> aero/derivative/CNr-per_deg </property>
						<property> velocities/r-deg_sec </property>
						<property> aero/bi2vel </property>
					</product>
					<property> aero/coefficient/dCN_Rud </property>
				</sum>
				<property> aero/qbar-psf </property>
				<property> metrics/Sw-sqft </property>
				<property> metrics/bw-ft </property>
			</product>
		</function>

	</axis>

</aerodynamics>

